[
  {
    "lat": 49.0,
    "lon": 18.0,
    "risk": 0.0,
    "alert": false,
    "ndvi_stress": 0.451,
    "elevation_m": 538.0,
    "slope_deg": 2.7,
    "shap_drivers": [
      {
        "feature": "wind_dryness_ratio",
        "shap": 0.0
      },
      {
        "feature": "dryness_ratio",
        "shap": 0.0
      },
      {
        "feature": "soil_x_rh",
        "shap": 0.0
      }
    ],
    "hourly_risk": [
      {
        "time": "2026-05-29T00:00",
        "risk": 0.0
      },
      {
        "time": "2026-05-29T01:00",
        "risk": 0.0
      },
      {
        "time": "2026-05-29T02:00",
        "risk": 0.0
      },
      {
        "time": "2026-05-29T03:00",
        "risk": 0.0
      },
      {
        "time": "2026-05-29T04:00",
        "risk": 0.0
      },
      {
        "time": "2026-05-29T05:00",
        "risk": 0.0
      },
      {
        "time": "2026-05-29T06:00",
        "risk": 0.0
      },
      {
        "time": "2026-05-29T07:00",
        "risk": 0.0
      },
      {
        "time": "2026-05-29T08:00",
        "risk": 0.0
      },
      {
        "time": "2026-05-29T09:00",
        "risk": 0.0
      },
      {
        "time": "2026-05-29T10:00",
        "risk": 0.0
      },
      {
        "time": "2026-05-29T11:00",
        "risk": 0.0
      },
      {
        "time": "2026-05-29T12:00",
        "risk": 0.0
      },
      {
        "time": "2026-05-29T13:00",
        "risk": 0.0
      },
      {
        "time": "2026-05-29T14:00",
        "risk": 0.0
      },
      {
        "time": "2026-05-29T15:00",
        "risk": 0.0
      },
      {
        "time": "2026-05-29T16:00",
        "risk": 0.0
      },
      {
        "time": "2026-05-29T17:00",
        "risk": 0.0
      },
      {
        "time": "2026-05-29T18:00",
        "risk": 0.0
      },
      {
        "time": "2026-05-29T19:00",
        "risk": 0.0
      },
      {
        "time": "2026-05-29T20:00",
        "risk": 0.0
      },
      {
        "time": "2026-05-29T21:00",
        "risk": 0.0
      },
      {
        "time": "2026-05-29T22:00",
        "risk": 0.0
      },
      {
        "time": "2026-05-29T23:00",
        "risk": 0.0
      }
    ]
  },
  {
    "lat": 49.0,
    "lon": 20.0,
    "risk": 0.0,
    "alert": false,
    "ndvi_stress": 0.408,
    "elevation_m": 1000.0,
    "slope_deg": 4.17,
    "shap_drivers": [
      {
        "feature": "wind_dryness_ratio",
        "shap": 0.0
      },
      {
        "feature": "dryness_ratio",
        "shap": 0.0
      },
      {
        "feature": "soil_x_rh",
        "shap": 0.0
      }
    ],
    "hourly_risk": [
      {
        "time": "2026-05-29T00:00",
        "risk": 0.0
      },
      {
        "time": "2026-05-29T01:00",
        "risk": 0.0
      },
      {
        "time": "2026-05-29T02:00",
        "risk": 0.0
      },
      {
        "time": "2026-05-29T03:00",
        "risk": 0.0
      },
      {
        "time": "2026-05-29T04:00",
        "risk": 0.0
      },
      {
        "time": "2026-05-29T05:00",
        "risk": 0.0
      },
      {
        "time": "2026-05-29T06:00",
        "risk": 0.0
      },
      {
        "time": "2026-05-29T07:00",
        "risk": 0.0
      },
      {
        "time": "2026-05-29T08:00",
        "risk": 0.0
      },
      {
        "time": "2026-05-29T09:00",
        "risk": 0.0
      },
      {
        "time": "2026-05-29T10:00",
        "risk": 0.0
      },
      {
        "time": "2026-05-29T11:00",
        "risk": 0.0
      },
      {
        "time": "2026-05-29T12:00",
        "risk": 0.0
      },
      {
        "time": "2026-05-29T13:00",
        "risk": 0.0
      },
      {
        "time": "2026-05-29T14:00",
        "risk": 0.0
      },
      {
        "time": "2026-05-29T15:00",
        "risk": 0.0
      },
      {
        "time": "2026-05-29T16:00",
        "risk": 0.0
      },
      {
        "time": "2026-05-29T17:00",
        "risk": 0.0
      },
      {
        "time": "2026-05-29T18:00",
        "risk": 0.0
      },
      {
        "time": "2026-05-29T19:00",
        "risk": 0.0
      },
      {
        "time": "2026-05-29T20:00",
        "risk": 0.0
      },
      {
        "time": "2026-05-29T21:00",
        "risk": 0.0
      },
      {
        "time": "2026-05-29T22:00",
        "risk": 0.0
      },
      {
        "time": "2026-05-29T23:00",
        "risk": 0.0
      }
    ]
  },
  {
    "lat": 50.1,
    "lon": 20.0,
    "risk": 0.0,
    "alert": false,
    "ndvi_stress": 0.433,
    "elevation_m": 200.0,
    "slope_deg": 0.71,
    "shap_drivers": [
      {
        "feature": "wind_dryness_ratio",
        "shap": 0.0
      },
      {
        "feature": "dryness_ratio",
        "shap": 0.0
      },
      {
        "feature": "soil_x_rh",
        "shap": 0.0
      }
    ],
    "hourly_risk": [
      {
        "time": "2026-05-29T00:00",
        "risk": 0.0
      },
      {
        "time": "2026-05-29T01:00",
        "risk": 0.0
      },
      {
        "time": "2026-05-29T02:00",
        "risk": 0.0
      },
      {
        "time": "2026-05-29T03:00",
        "risk": 0.0
      },
      {
        "time": "2026-05-29T04:00",
        "risk": 0.0
      },
      {
        "time": "2026-05-29T05:00",
        "risk": 0.0
      },
      {
        "time": "2026-05-29T06:00",
        "risk": 0.0
      },
      {
        "time": "2026-05-29T07:00",
        "risk": 0.0
      },
      {
        "time": "2026-05-29T08:00",
        "risk": 0.0
      },
      {
        "time": "2026-05-29T09:00",
        "risk": 0.0
      },
      {
        "time": "2026-05-29T10:00",
        "risk": 0.0
      },
      {
        "time": "2026-05-29T11:00",
        "risk": 0.0
      },
      {
        "time": "2026-05-29T12:00",
        "risk": 0.0
      },
      {
        "time": "2026-05-29T13:00",
        "risk": 0.0
      },
      {
        "time": "2026-05-29T14:00",
        "risk": 0.0
      },
      {
        "time": "2026-05-29T15:00",
        "risk": 0.0
      },
      {
        "time": "2026-05-29T16:00",
        "risk": 0.0
      },
      {
        "time": "2026-05-29T17:00",
        "risk": 0.0
      },
      {
        "time": "2026-05-29T18:00",
        "risk": 0.0
      },
      {
        "time": "2026-05-29T19:00",
        "risk": 0.0
      },
      {
        "time": "2026-05-29T20:00",
        "risk": 0.0
      },
      {
        "time": "2026-05-29T21:00",
        "risk": 0.0
      },
      {
        "time": "2026-05-29T22:00",
        "risk": 0.0
      },
      {
        "time": "2026-05-29T23:00",
        "risk": 0.0
      }
    ]
  },
  {
    "lat": 49.0,
    "lon": 14.0,
    "risk": 0.0,
    "alert": false,
    "ndvi_stress": 0.475,
    "elevation_m": 200.0,
    "slope_deg": 4.24,
    "shap_drivers": [
      {
        "feature": "wind_dryness_ratio",
        "shap": 0.0
      },
      {
        "feature": "dryness_ratio",
        "shap": 0.0
      },
      {
        "feature": "soil_x_rh",
        "shap": 0.0
      }
    ],
    "hourly_risk": [
      {
        "time": "2026-05-29T00:00",
        "risk": 0.0
      },
      {
        "time": "2026-05-29T01:00",
        "risk": 0.0
      },
      {
        "time": "2026-05-29T02:00",
        "risk": 0.0
      },
      {
        "time": "2026-05-29T03:00",
        "risk": 0.0
      },
      {
        "time": "2026-05-29T04:00",
        "risk": 0.0
      },
      {
        "time": "2026-05-29T05:00",
        "risk": 0.0
      },
      {
        "time": "2026-05-29T06:00",
        "risk": 0.0
      },
      {
        "time": "2026-05-29T07:00",
        "risk": 0.0
      },
      {
        "time": "2026-05-29T08:00",
        "risk": 0.0
      },
      {
        "time": "2026-05-29T09:00",
        "risk": 0.0
      },
      {
        "time": "2026-05-29T10:00",
        "risk": 0.0
      },
      {
        "time": "2026-05-29T11:00",
        "risk": 0.0
      },
      {
        "time": "2026-05-29T12:00",
        "risk": 0.0
      },
      {
        "time": "2026-05-29T13:00",
        "risk": 0.0
      },
      {
        "time": "2026-05-29T14:00",
        "risk": 0.0
      },
      {
        "time": "2026-05-29T15:00",
        "risk": 0.0
      },
      {
        "time": "2026-05-29T16:00",
        "risk": 0.0
      },
      {
        "time": "2026-05-29T17:00",
        "risk": 0.0
      },
      {
        "time": "2026-05-29T18:00",
        "risk": 0.0
      },
      {
        "time": "2026-05-29T19:00",
        "risk": 0.0
      },
      {
        "time": "2026-05-29T20:00",
        "risk": 0.0
      },
      {
        "time": "2026-05-29T21:00",
        "risk": 0.0
      },
      {
        "time": "2026-05-29T22:00",
        "risk": 0.0
      },
      {
        "time": "2026-05-29T23:00",
        "risk": 0.0
      }
    ]
  },
  {
    "lat": 50.1,
    "lon": 16.0,
    "risk": 0.0,
    "alert": false,
    "ndvi_stress": 0.563,
    "elevation_m": 317.0,
    "slope_deg": 0.59,
    "shap_drivers": [
      {
        "feature": "wind_dryness_ratio",
        "shap": 0.0
      },
      {
        "feature": "dryness_ratio",
        "shap": 0.0
      },
      {
        "feature": "soil_x_rh",
        "shap": 0.0
      }
    ],
    "hourly_risk": [
      {
        "time": "2026-05-29T00:00",
        "risk": 0.0
      },
      {
        "time": "2026-05-29T01:00",
        "risk": 0.0
      },
      {
        "time": "2026-05-29T02:00",
        "risk": 0.0
      },
      {
        "time": "2026-05-29T03:00",
        "risk": 0.0
      },
      {
        "time": "2026-05-29T04:00",
        "risk": 0.0
      },
      {
        "time": "2026-05-29T05:00",
        "risk": 0.0
      },
      {
        "time": "2026-05-29T06:00",
        "risk": 0.0
      },
      {
        "time": "2026-05-29T07:00",
        "risk": 0.0
      },
      {
        "time": "2026-05-29T08:00",
        "risk": 0.0
      },
      {
        "time": "2026-05-29T09:00",
        "risk": 0.0
      },
      {
        "time": "2026-05-29T10:00",
        "risk": 0.0
      },
      {
        "time": "2026-05-29T11:00",
        "risk": 0.0
      },
      {
        "time": "2026-05-29T12:00",
        "risk": 0.0
      },
      {
        "time": "2026-05-29T13:00",
        "risk": 0.0
      },
      {
        "time": "2026-05-29T14:00",
        "risk": 0.0
      },
      {
        "time": "2026-05-29T15:00",
        "risk": 0.0
      },
      {
        "time": "2026-05-29T16:00",
        "risk": 0.0
      },
      {
        "time": "2026-05-29T17:00",
        "risk": 0.0
      },
      {
        "time": "2026-05-29T18:00",
        "risk": 0.0
      },
      {
        "time": "2026-05-29T19:00",
        "risk": 0.0
      },
      {
        "time": "2026-05-29T20:00",
        "risk": 0.0
      },
      {
        "time": "2026-05-29T21:00",
        "risk": 0.0
      },
      {
        "time": "2026-05-29T22:00",
        "risk": 0.0
      },
      {
        "time": "2026-05-29T23:00",
        "risk": 0.0
      }
    ]
  },
  {
    "lat": 49.0,
    "lon": 24.0,
    "risk": 0.0,
    "alert": false,
    "ndvi_stress": 0.338,
    "elevation_m": 418.0,
    "slope_deg": 0.56,
    "shap_drivers": [
      {
        "feature": "wind_dryness_ratio",
        "shap": 0.0
      },
      {
        "feature": "dryness_ratio",
        "shap": 0.0
      },
      {
        "feature": "soil_x_rh",
        "shap": 0.0
      }
    ],
    "hourly_risk": [
      {
        "time": "2026-05-29T00:00",
        "risk": 0.0
      },
      {
        "time": "2026-05-29T01:00",
        "risk": 0.0
      },
      {
        "time": "2026-05-29T02:00",
        "risk": 0.0
      },
      {
        "time": "2026-05-29T03:00",
        "risk": 0.0
      },
      {
        "time": "2026-05-29T04:00",
        "risk": 0.0
      },
      {
        "time": "2026-05-29T05:00",
        "risk": 0.0
      },
      {
        "time": "2026-05-29T06:00",
        "risk": 0.0
      },
      {
        "time": "2026-05-29T07:00",
        "risk": 0.0
      },
      {
        "time": "2026-05-29T08:00",
        "risk": 0.0
      },
      {
        "time": "2026-05-29T09:00",
        "risk": 0.0
      },
      {
        "time": "2026-05-29T10:00",
        "risk": 0.0
      },
      {
        "time": "2026-05-29T11:00",
        "risk": 0.0
      },
      {
        "time": "2026-05-29T12:00",
        "risk": 0.0
      },
      {
        "time": "2026-05-29T13:00",
        "risk": 0.0
      },
      {
        "time": "2026-05-29T14:00",
        "risk": 0.0
      },
      {
        "time": "2026-05-29T15:00",
        "risk": 0.0
      },
      {
        "time": "2026-05-29T16:00",
        "risk": 0.0
      },
      {
        "time": "2026-05-29T17:00",
        "risk": 0.0
      },
      {
        "time": "2026-05-29T18:00",
        "risk": 0.0
      },
      {
        "time": "2026-05-29T19:00",
        "risk": 0.0
      },
      {
        "time": "2026-05-29T20:00",
        "risk": 0.0
      },
      {
        "time": "2026-05-29T21:00",
        "risk": 0.0
      },
      {
        "time": "2026-05-29T22:00",
        "risk": 0.0
      },
      {
        "time": "2026-05-29T23:00",
        "risk": 0.0
      }
    ]
  },
  {
    "lat": 49.0,
    "lon": 22.0,
    "risk": 0.0,
    "alert": false,
    "ndvi_stress": 0.433,
    "elevation_m": 213.0,
    "slope_deg": 1.13,
    "shap_drivers": [
      {
        "feature": "wind_dryness_ratio",
        "shap": 0.0
      },
      {
        "feature": "dryness_ratio",
        "shap": 0.0
      },
      {
        "feature": "soil_x_rh",
        "shap": 0.0
      }
    ],
    "hourly_risk": [
      {
        "time": "2026-05-29T00:00",
        "risk": 0.0
      },
      {
        "time": "2026-05-29T01:00",
        "risk": 0.0
      },
      {
        "time": "2026-05-29T02:00",
        "risk": 0.0
      },
      {
        "time": "2026-05-29T03:00",
        "risk": 0.0
      },
      {
        "time": "2026-05-29T04:00",
        "risk": 0.0
      },
      {
        "time": "2026-05-29T05:00",
        "risk": 0.0
      },
      {
        "time": "2026-05-29T06:00",
        "risk": 0.0
      },
      {
        "time": "2026-05-29T07:00",
        "risk": 0.0
      },
      {
        "time": "2026-05-29T08:00",
        "risk": 0.0
      },
      {
        "time": "2026-05-29T09:00",
        "risk": 0.0
      },
      {
        "time": "2026-05-29T10:00",
        "risk": 0.0
      },
      {
        "time": "2026-05-29T11:00",
        "risk": 0.0
      },
      {
        "time": "2026-05-29T12:00",
        "risk": 0.0
      },
      {
        "time": "2026-05-29T13:00",
        "risk": 0.0
      },
      {
        "time": "2026-05-29T14:00",
        "risk": 0.0
      },
      {
        "time": "2026-05-29T15:00",
        "risk": 0.0
      },
      {
        "time": "2026-05-29T16:00",
        "risk": 0.0
      },
      {
        "time": "2026-05-29T17:00",
        "risk": 0.0
      },
      {
        "time": "2026-05-29T18:00",
        "risk": 0.0
      },
      {
        "time": "2026-05-29T19:00",
        "risk": 0.0
      },
      {
        "time": "2026-05-29T20:00",
        "risk": 0.0
      },
      {
        "time": "2026-05-29T21:00",
        "risk": 0.0
      },
      {
        "time": "2026-05-29T22:00",
        "risk": 0.0
      },
      {
        "time": "2026-05-29T23:00",
        "risk": 0.0
      }
    ]
  },
  {
    "lat": 49.0,
    "lon": 16.0,
    "risk": 0.0,
    "alert": false,
    "ndvi_stress": 0.483,
    "elevation_m": 321.0,
    "slope_deg": 0.75,
    "shap_drivers": [
      {
        "feature": "wind_dryness_ratio",
        "shap": 0.0
      },
      {
        "feature": "dryness_ratio",
        "shap": 0.0
      },
      {
        "feature": "soil_x_rh",
        "shap": 0.0
      }
    ],
    "hourly_risk": [
      {
        "time": "2026-05-29T00:00",
        "risk": 0.0
      },
      {
        "time": "2026-05-29T01:00",
        "risk": 0.0
      },
      {
        "time": "2026-05-29T02:00",
        "risk": 0.0
      },
      {
        "time": "2026-05-29T03:00",
        "risk": 0.0
      },
      {
        "time": "2026-05-29T04:00",
        "risk": 0.0
      },
      {
        "time": "2026-05-29T05:00",
        "risk": 0.0
      },
      {
        "time": "2026-05-29T06:00",
        "risk": 0.0
      },
      {
        "time": "2026-05-29T07:00",
        "risk": 0.0
      },
      {
        "time": "2026-05-29T08:00",
        "risk": 0.0
      },
      {
        "time": "2026-05-29T09:00",
        "risk": 0.0
      },
      {
        "time": "2026-05-29T10:00",
        "risk": 0.0
      },
      {
        "time": "2026-05-29T11:00",
        "risk": 0.0
      },
      {
        "time": "2026-05-29T12:00",
        "risk": 0.0
      },
      {
        "time": "2026-05-29T13:00",
        "risk": 0.0
      },
      {
        "time": "2026-05-29T14:00",
        "risk": 0.0
      },
      {
        "time": "2026-05-29T15:00",
        "risk": 0.0
      },
      {
        "time": "2026-05-29T16:00",
        "risk": 0.0
      },
      {
        "time": "2026-05-29T17:00",
        "risk": 0.0
      },
      {
        "time": "2026-05-29T18:00",
        "risk": 0.0
      },
      {
        "time": "2026-05-29T19:00",
        "risk": 0.0
      },
      {
        "time": "2026-05-29T20:00",
        "risk": 0.0
      },
      {
        "time": "2026-05-29T21:00",
        "risk": 0.0
      },
      {
        "time": "2026-05-29T22:00",
        "risk": 0.0
      },
      {
        "time": "2026-05-29T23:00",
        "risk": 0.0
      }
    ]
  },
  {
    "lat": 50.1,
    "lon": 18.0,
    "risk": 0.0,
    "alert": false,
    "ndvi_stress": 0.394,
    "elevation_m": 258.0,
    "slope_deg": 0.19,
    "shap_drivers": [
      {
        "feature": "wind_dryness_ratio",
        "shap": 0.0
      },
      {
        "feature": "dryness_ratio",
        "shap": 0.0
      },
      {
        "feature": "soil_x_rh",
        "shap": 0.0
      }
    ],
    "hourly_risk": [
      {
        "time": "2026-05-29T00:00",
        "risk": 0.0
      },
      {
        "time": "2026-05-29T01:00",
        "risk": 0.0
      },
      {
        "time": "2026-05-29T02:00",
        "risk": 0.0
      },
      {
        "time": "2026-05-29T03:00",
        "risk": 0.0
      },
      {
        "time": "2026-05-29T04:00",
        "risk": 0.0
      },
      {
        "time": "2026-05-29T05:00",
        "risk": 0.0
      },
      {
        "time": "2026-05-29T06:00",
        "risk": 0.0
      },
      {
        "time": "2026-05-29T07:00",
        "risk": 0.0
      },
      {
        "time": "2026-05-29T08:00",
        "risk": 0.0
      },
      {
        "time": "2026-05-29T09:00",
        "risk": 0.0
      },
      {
        "time": "2026-05-29T10:00",
        "risk": 0.0
      },
      {
        "time": "2026-05-29T11:00",
        "risk": 0.0
      },
      {
        "time": "2026-05-29T12:00",
        "risk": 0.0
      },
      {
        "time": "2026-05-29T13:00",
        "risk": 0.0
      },
      {
        "time": "2026-05-29T14:00",
        "risk": 0.0
      },
      {
        "time": "2026-05-29T15:00",
        "risk": 0.0
      },
      {
        "time": "2026-05-29T16:00",
        "risk": 0.0
      },
      {
        "time": "2026-05-29T17:00",
        "risk": 0.0
      },
      {
        "time": "2026-05-29T18:00",
        "risk": 0.0
      },
      {
        "time": "2026-05-29T19:00",
        "risk": 0.0
      },
      {
        "time": "2026-05-29T20:00",
        "risk": 0.0
      },
      {
        "time": "2026-05-29T21:00",
        "risk": 0.0
      },
      {
        "time": "2026-05-29T22:00",
        "risk": 0.0
      },
      {
        "time": "2026-05-29T23:00",
        "risk": 0.0
      }
    ]
  },
  {
    "lat": 50.1,
    "lon": 14.0,
    "risk": 0.0,
    "alert": false,
    "ndvi_stress": 0.539,
    "elevation_m": 398.0,
    "slope_deg": 0.25,
    "shap_drivers": [
      {
        "feature": "wind_dryness_ratio",
        "shap": 0.0
      },
      {
        "feature": "dryness_ratio",
        "shap": 0.0
      },
      {
        "feature": "soil_x_rh",
        "shap": 0.0
      }
    ],
    "hourly_risk": [
      {
        "time": "2026-05-29T00:00",
        "risk": 0.0
      },
      {
        "time": "2026-05-29T01:00",
        "risk": 0.0
      },
      {
        "time": "2026-05-29T02:00",
        "risk": 0.0
      },
      {
        "time": "2026-05-29T03:00",
        "risk": 0.0
      },
      {
        "time": "2026-05-29T04:00",
        "risk": 0.0
      },
      {
        "time": "2026-05-29T05:00",
        "risk": 0.0
      },
      {
        "time": "2026-05-29T06:00",
        "risk": 0.0
      },
      {
        "time": "2026-05-29T07:00",
        "risk": 0.0
      },
      {
        "time": "2026-05-29T08:00",
        "risk": 0.0
      },
      {
        "time": "2026-05-29T09:00",
        "risk": 0.0
      },
      {
        "time": "2026-05-29T10:00",
        "risk": 0.0
      },
      {
        "time": "2026-05-29T11:00",
        "risk": 0.0
      },
      {
        "time": "2026-05-29T12:00",
        "risk": 0.0
      },
      {
        "time": "2026-05-29T13:00",
        "risk": 0.0
      },
      {
        "time": "2026-05-29T14:00",
        "risk": 0.0
      },
      {
        "time": "2026-05-29T15:00",
        "risk": 0.0
      },
      {
        "time": "2026-05-29T16:00",
        "risk": 0.0
      },
      {
        "time": "2026-05-29T17:00",
        "risk": 0.0
      },
      {
        "time": "2026-05-29T18:00",
        "risk": 0.0
      },
      {
        "time": "2026-05-29T19:00",
        "risk": 0.0
      },
      {
        "time": "2026-05-29T20:00",
        "risk": 0.0
      },
      {
        "time": "2026-05-29T21:00",
        "risk": 0.0
      },
      {
        "time": "2026-05-29T22:00",
        "risk": 0.0
      },
      {
        "time": "2026-05-29T23:00",
        "risk": 0.0
      }
    ]
  },
  {
    "lat": 51.2,
    "lon": 16.0,
    "risk": 0.0,
    "alert": false,
    "ndvi_stress": 0.589,
    "elevation_m": 177.0,
    "slope_deg": 0.31,
    "shap_drivers": [
      {
        "feature": "wind_dryness_ratio",
        "shap": 0.0
      },
      {
        "feature": "dryness_ratio",
        "shap": 0.0
      },
      {
        "feature": "soil_x_rh",
        "shap": 0.0
      }
    ],
    "hourly_risk": [
      {
        "time": "2026-05-29T00:00",
        "risk": 0.0
      },
      {
        "time": "2026-05-29T01:00",
        "risk": 0.0
      },
      {
        "time": "2026-05-29T02:00",
        "risk": 0.0
      },
      {
        "time": "2026-05-29T03:00",
        "risk": 0.0
      },
      {
        "time": "2026-05-29T04:00",
        "risk": 0.0
      },
      {
        "time": "2026-05-29T05:00",
        "risk": 0.0
      },
      {
        "time": "2026-05-29T06:00",
        "risk": 0.0
      },
      {
        "time": "2026-05-29T07:00",
        "risk": 0.0
      },
      {
        "time": "2026-05-29T08:00",
        "risk": 0.0
      },
      {
        "time": "2026-05-29T09:00",
        "risk": 0.0
      },
      {
        "time": "2026-05-29T10:00",
        "risk": 0.0
      },
      {
        "time": "2026-05-29T11:00",
        "risk": 0.0
      },
      {
        "time": "2026-05-29T12:00",
        "risk": 0.0
      },
      {
        "time": "2026-05-29T13:00",
        "risk": 0.0
      },
      {
        "time": "2026-05-29T14:00",
        "risk": 0.0
      },
      {
        "time": "2026-05-29T15:00",
        "risk": 0.0
      },
      {
        "time": "2026-05-29T16:00",
        "risk": 0.0
      },
      {
        "time": "2026-05-29T17:00",
        "risk": 0.0
      },
      {
        "time": "2026-05-29T18:00",
        "risk": 0.0
      },
      {
        "time": "2026-05-29T19:00",
        "risk": 0.0
      },
      {
        "time": "2026-05-29T20:00",
        "risk": 0.0
      },
      {
        "time": "2026-05-29T21:00",
        "risk": 0.0
      },
      {
        "time": "2026-05-29T22:00",
        "risk": 0.0
      },
      {
        "time": "2026-05-29T23:00",
        "risk": 0.0
      }
    ]
  },
  {
    "lat": 51.2,
    "lon": 14.0,
    "risk": 0.0,
    "alert": false,
    "ndvi_stress": 0.558,
    "elevation_m": 255.0,
    "slope_deg": 0.61,
    "shap_drivers": [
      {
        "feature": "wind_dryness_ratio",
        "shap": 0.0
      },
      {
        "feature": "dryness_ratio",
        "shap": 0.0
      },
      {
        "feature": "soil_x_rh",
        "shap": 0.0
      }
    ],
    "hourly_risk": [
      {
        "time": "2026-05-29T00:00",
        "risk": 0.0
      },
      {
        "time": "2026-05-29T01:00",
        "risk": 0.0
      },
      {
        "time": "2026-05-29T02:00",
        "risk": 0.0
      },
      {
        "time": "2026-05-29T03:00",
        "risk": 0.0
      },
      {
        "time": "2026-05-29T04:00",
        "risk": 0.0
      },
      {
        "time": "2026-05-29T05:00",
        "risk": 0.0
      },
      {
        "time": "2026-05-29T06:00",
        "risk": 0.0
      },
      {
        "time": "2026-05-29T07:00",
        "risk": 0.0
      },
      {
        "time": "2026-05-29T08:00",
        "risk": 0.0
      },
      {
        "time": "2026-05-29T09:00",
        "risk": 0.0
      },
      {
        "time": "2026-05-29T10:00",
        "risk": 0.0
      },
      {
        "time": "2026-05-29T11:00",
        "risk": 0.0
      },
      {
        "time": "2026-05-29T12:00",
        "risk": 0.0
      },
      {
        "time": "2026-05-29T13:00",
        "risk": 0.0
      },
      {
        "time": "2026-05-29T14:00",
        "risk": 0.0
      },
      {
        "time": "2026-05-29T15:00",
        "risk": 0.0
      },
      {
        "time": "2026-05-29T16:00",
        "risk": 0.0
      },
      {
        "time": "2026-05-29T17:00",
        "risk": 0.0
      },
      {
        "time": "2026-05-29T18:00",
        "risk": 0.0
      },
      {
        "time": "2026-05-29T19:00",
        "risk": 0.0
      },
      {
        "time": "2026-05-29T20:00",
        "risk": 0.0
      },
      {
        "time": "2026-05-29T21:00",
        "risk": 0.0
      },
      {
        "time": "2026-05-29T22:00",
        "risk": 0.0
      },
      {
        "time": "2026-05-29T23:00",
        "risk": 0.0
      }
    ]
  },
  {
    "lat": 50.1,
    "lon": 24.0,
    "risk": 0.0,
    "alert": false,
    "ndvi_stress": 0.456,
    "elevation_m": 220.0,
    "slope_deg": 0.03,
    "shap_drivers": [
      {
        "feature": "wind_dryness_ratio",
        "shap": 0.0
      },
      {
        "feature": "dryness_ratio",
        "shap": 0.0
      },
      {
        "feature": "soil_x_rh",
        "shap": 0.0
      }
    ],
    "hourly_risk": [
      {
        "time": "2026-05-29T00:00",
        "risk": 0.0
      },
      {
        "time": "2026-05-29T01:00",
        "risk": 0.0
      },
      {
        "time": "2026-05-29T02:00",
        "risk": 0.0
      },
      {
        "time": "2026-05-29T03:00",
        "risk": 0.0
      },
      {
        "time": "2026-05-29T04:00",
        "risk": 0.0
      },
      {
        "time": "2026-05-29T05:00",
        "risk": 0.0
      },
      {
        "time": "2026-05-29T06:00",
        "risk": 0.0
      },
      {
        "time": "2026-05-29T07:00",
        "risk": 0.0
      },
      {
        "time": "2026-05-29T08:00",
        "risk": 0.0
      },
      {
        "time": "2026-05-29T09:00",
        "risk": 0.0
      },
      {
        "time": "2026-05-29T10:00",
        "risk": 0.0
      },
      {
        "time": "2026-05-29T11:00",
        "risk": 0.0
      },
      {
        "time": "2026-05-29T12:00",
        "risk": 0.0
      },
      {
        "time": "2026-05-29T13:00",
        "risk": 0.0
      },
      {
        "time": "2026-05-29T14:00",
        "risk": 0.0
      },
      {
        "time": "2026-05-29T15:00",
        "risk": 0.0
      },
      {
        "time": "2026-05-29T16:00",
        "risk": 0.0
      },
      {
        "time": "2026-05-29T17:00",
        "risk": 0.0
      },
      {
        "time": "2026-05-29T18:00",
        "risk": 0.0
      },
      {
        "time": "2026-05-29T19:00",
        "risk": 0.0
      },
      {
        "time": "2026-05-29T20:00",
        "risk": 0.0
      },
      {
        "time": "2026-05-29T21:00",
        "risk": 0.0
      },
      {
        "time": "2026-05-29T22:00",
        "risk": 0.0
      },
      {
        "time": "2026-05-29T23:00",
        "risk": 0.0
      }
    ]
  },
  {
    "lat": 50.1,
    "lon": 22.0,
    "risk": 0.0,
    "alert": false,
    "ndvi_stress": 0.523,
    "elevation_m": 205.0,
    "slope_deg": 0.25,
    "shap_drivers": [
      {
        "feature": "wind_dryness_ratio",
        "shap": 0.0
      },
      {
        "feature": "dryness_ratio",
        "shap": 0.0
      },
      {
        "feature": "soil_x_rh",
        "shap": 0.0
      }
    ],
    "hourly_risk": [
      {
        "time": "2026-05-29T00:00",
        "risk": 0.0
      },
      {
        "time": "2026-05-29T01:00",
        "risk": 0.0
      },
      {
        "time": "2026-05-29T02:00",
        "risk": 0.0
      },
      {
        "time": "2026-05-29T03:00",
        "risk": 0.0
      },
      {
        "time": "2026-05-29T04:00",
        "risk": 0.0
      },
      {
        "time": "2026-05-29T05:00",
        "risk": 0.0
      },
      {
        "time": "2026-05-29T06:00",
        "risk": 0.0
      },
      {
        "time": "2026-05-29T07:00",
        "risk": 0.0
      },
      {
        "time": "2026-05-29T08:00",
        "risk": 0.0
      },
      {
        "time": "2026-05-29T09:00",
        "risk": 0.0
      },
      {
        "time": "2026-05-29T10:00",
        "risk": 0.0
      },
      {
        "time": "2026-05-29T11:00",
        "risk": 0.0
      },
      {
        "time": "2026-05-29T12:00",
        "risk": 0.0
      },
      {
        "time": "2026-05-29T13:00",
        "risk": 0.0
      },
      {
        "time": "2026-05-29T14:00",
        "risk": 0.0
      },
      {
        "time": "2026-05-29T15:00",
        "risk": 0.0
      },
      {
        "time": "2026-05-29T16:00",
        "risk": 0.0
      },
      {
        "time": "2026-05-29T17:00",
        "risk": 0.0
      },
      {
        "time": "2026-05-29T18:00",
        "risk": 0.0
      },
      {
        "time": "2026-05-29T19:00",
        "risk": 0.0
      },
      {
        "time": "2026-05-29T20:00",
        "risk": 0.0
      },
      {
        "time": "2026-05-29T21:00",
        "risk": 0.0
      },
      {
        "time": "2026-05-29T22:00",
        "risk": 0.0
      },
      {
        "time": "2026-05-29T23:00",
        "risk": 0.0
      }
    ]
  },
  {
    "lat": 51.2,
    "lon": 18.0,
    "risk": 0.0,
    "alert": false,
    "ndvi_stress": 0.526,
    "elevation_m": 212.0,
    "slope_deg": 0.39,
    "shap_drivers": [
      {
        "feature": "wind_dryness_ratio",
        "shap": 0.0
      },
      {
        "feature": "dryness_ratio",
        "shap": 0.0
      },
      {
        "feature": "soil_x_rh",
        "shap": 0.0
      }
    ],
    "hourly_risk": [
      {
        "time": "2026-05-29T00:00",
        "risk": 0.0
      },
      {
        "time": "2026-05-29T01:00",
        "risk": 0.0
      },
      {
        "time": "2026-05-29T02:00",
        "risk": 0.0
      },
      {
        "time": "2026-05-29T03:00",
        "risk": 0.0
      },
      {
        "time": "2026-05-29T04:00",
        "risk": 0.0
      },
      {
        "time": "2026-05-29T05:00",
        "risk": 0.0
      },
      {
        "time": "2026-05-29T06:00",
        "risk": 0.0
      },
      {
        "time": "2026-05-29T07:00",
        "risk": 0.0
      },
      {
        "time": "2026-05-29T08:00",
        "risk": 0.0
      },
      {
        "time": "2026-05-29T09:00",
        "risk": 0.0
      },
      {
        "time": "2026-05-29T10:00",
        "risk": 0.0
      },
      {
        "time": "2026-05-29T11:00",
        "risk": 0.0
      },
      {
        "time": "2026-05-29T12:00",
        "risk": 0.0
      },
      {
        "time": "2026-05-29T13:00",
        "risk": 0.0
      },
      {
        "time": "2026-05-29T14:00",
        "risk": 0.0
      },
      {
        "time": "2026-05-29T15:00",
        "risk": 0.0
      },
      {
        "time": "2026-05-29T16:00",
        "risk": 0.0
      },
      {
        "time": "2026-05-29T17:00",
        "risk": 0.0
      },
      {
        "time": "2026-05-29T18:00",
        "risk": 0.0
      },
      {
        "time": "2026-05-29T19:00",
        "risk": 0.0
      },
      {
        "time": "2026-05-29T20:00",
        "risk": 0.0
      },
      {
        "time": "2026-05-29T21:00",
        "risk": 0.0
      },
      {
        "time": "2026-05-29T22:00",
        "risk": 0.0
      },
      {
        "time": "2026-05-29T23:00",
        "risk": 0.0
      }
    ]
  },
  {
    "lat": 51.2,
    "lon": 22.0,
    "risk": 0.0,
    "alert": false,
    "ndvi_stress": 0.52,
    "elevation_m": 156.0,
    "slope_deg": 0.41,
    "shap_drivers": [
      {
        "feature": "wind_dryness_ratio",
        "shap": 0.0
      },
      {
        "feature": "dryness_ratio",
        "shap": 0.0
      },
      {
        "feature": "soil_x_rh",
        "shap": 0.0
      }
    ],
    "hourly_risk": [
      {
        "time": "2026-05-29T00:00",
        "risk": 0.0
      },
      {
        "time": "2026-05-29T01:00",
        "risk": 0.0
      },
      {
        "time": "2026-05-29T02:00",
        "risk": 0.0
      },
      {
        "time": "2026-05-29T03:00",
        "risk": 0.0
      },
      {
        "time": "2026-05-29T04:00",
        "risk": 0.0
      },
      {
        "time": "2026-05-29T05:00",
        "risk": 0.0
      },
      {
        "time": "2026-05-29T06:00",
        "risk": 0.0
      },
      {
        "time": "2026-05-29T07:00",
        "risk": 0.0
      },
      {
        "time": "2026-05-29T08:00",
        "risk": 0.0
      },
      {
        "time": "2026-05-29T09:00",
        "risk": 0.0
      },
      {
        "time": "2026-05-29T10:00",
        "risk": 0.0
      },
      {
        "time": "2026-05-29T11:00",
        "risk": 0.0
      },
      {
        "time": "2026-05-29T12:00",
        "risk": 0.0
      },
      {
        "time": "2026-05-29T13:00",
        "risk": 0.0
      },
      {
        "time": "2026-05-29T14:00",
        "risk": 0.0
      },
      {
        "time": "2026-05-29T15:00",
        "risk": 0.0
      },
      {
        "time": "2026-05-29T16:00",
        "risk": 0.0
      },
      {
        "time": "2026-05-29T17:00",
        "risk": 0.0
      },
      {
        "time": "2026-05-29T18:00",
        "risk": 0.0
      },
      {
        "time": "2026-05-29T19:00",
        "risk": 0.0
      },
      {
        "time": "2026-05-29T20:00",
        "risk": 0.0
      },
      {
        "time": "2026-05-29T21:00",
        "risk": 0.0
      },
      {
        "time": "2026-05-29T22:00",
        "risk": 0.0
      },
      {
        "time": "2026-05-29T23:00",
        "risk": 0.0
      }
    ]
  },
  {
    "lat": 51.2,
    "lon": 20.0,
    "risk": 0.0,
    "alert": false,
    "ndvi_stress": 0.522,
    "elevation_m": 224.0,
    "slope_deg": 0.32,
    "shap_drivers": [
      {
        "feature": "wind_dryness_ratio",
        "shap": 0.0
      },
      {
        "feature": "dryness_ratio",
        "shap": 0.0
      },
      {
        "feature": "soil_x_rh",
        "shap": 0.0
      }
    ],
    "hourly_risk": [
      {
        "time": "2026-05-29T00:00",
        "risk": 0.0
      },
      {
        "time": "2026-05-29T01:00",
        "risk": 0.0
      },
      {
        "time": "2026-05-29T02:00",
        "risk": 0.0
      },
      {
        "time": "2026-05-29T03:00",
        "risk": 0.0
      },
      {
        "time": "2026-05-29T04:00",
        "risk": 0.0
      },
      {
        "time": "2026-05-29T05:00",
        "risk": 0.0
      },
      {
        "time": "2026-05-29T06:00",
        "risk": 0.0
      },
      {
        "time": "2026-05-29T07:00",
        "risk": 0.0
      },
      {
        "time": "2026-05-29T08:00",
        "risk": 0.0
      },
      {
        "time": "2026-05-29T09:00",
        "risk": 0.0
      },
      {
        "time": "2026-05-29T10:00",
        "risk": 0.0
      },
      {
        "time": "2026-05-29T11:00",
        "risk": 0.0
      },
      {
        "time": "2026-05-29T12:00",
        "risk": 0.0
      },
      {
        "time": "2026-05-29T13:00",
        "risk": 0.0
      },
      {
        "time": "2026-05-29T14:00",
        "risk": 0.0
      },
      {
        "time": "2026-05-29T15:00",
        "risk": 0.0
      },
      {
        "time": "2026-05-29T16:00",
        "risk": 0.0
      },
      {
        "time": "2026-05-29T17:00",
        "risk": 0.0
      },
      {
        "time": "2026-05-29T18:00",
        "risk": 0.0
      },
      {
        "time": "2026-05-29T19:00",
        "risk": 0.0
      },
      {
        "time": "2026-05-29T20:00",
        "risk": 0.0
      },
      {
        "time": "2026-05-29T21:00",
        "risk": 0.0
      },
      {
        "time": "2026-05-29T22:00",
        "risk": 0.0
      },
      {
        "time": "2026-05-29T23:00",
        "risk": 0.0
      }
    ]
  },
  {
    "lat": 52.3,
    "lon": 14.0,
    "risk": 0.0,
    "alert": false,
    "ndvi_stress": 0.51,
    "elevation_m": 58.0,
    "slope_deg": 0.11,
    "shap_drivers": [
      {
        "feature": "wind_dryness_ratio",
        "shap": 0.0
      },
      {
        "feature": "dryness_ratio",
        "shap": 0.0
      },
      {
        "feature": "soil_x_rh",
        "shap": 0.0
      }
    ],
    "hourly_risk": [
      {
        "time": "2026-05-29T00:00",
        "risk": 0.0
      },
      {
        "time": "2026-05-29T01:00",
        "risk": 0.0
      },
      {
        "time": "2026-05-29T02:00",
        "risk": 0.0
      },
      {
        "time": "2026-05-29T03:00",
        "risk": 0.0
      },
      {
        "time": "2026-05-29T04:00",
        "risk": 0.0
      },
      {
        "time": "2026-05-29T05:00",
        "risk": 0.0
      },
      {
        "time": "2026-05-29T06:00",
        "risk": 0.0
      },
      {
        "time": "2026-05-29T07:00",
        "risk": 0.0
      },
      {
        "time": "2026-05-29T08:00",
        "risk": 0.0
      },
      {
        "time": "2026-05-29T09:00",
        "risk": 0.0
      },
      {
        "time": "2026-05-29T10:00",
        "risk": 0.0
      },
      {
        "time": "2026-05-29T11:00",
        "risk": 0.0
      },
      {
        "time": "2026-05-29T12:00",
        "risk": 0.0
      },
      {
        "time": "2026-05-29T13:00",
        "risk": 0.0
      },
      {
        "time": "2026-05-29T14:00",
        "risk": 0.0
      },
      {
        "time": "2026-05-29T15:00",
        "risk": 0.0
      },
      {
        "time": "2026-05-29T16:00",
        "risk": 0.0
      },
      {
        "time": "2026-05-29T17:00",
        "risk": 0.0
      },
      {
        "time": "2026-05-29T18:00",
        "risk": 0.0
      },
      {
        "time": "2026-05-29T19:00",
        "risk": 0.0
      },
      {
        "time": "2026-05-29T20:00",
        "risk": 0.0
      },
      {
        "time": "2026-05-29T21:00",
        "risk": 0.0
      },
      {
        "time": "2026-05-29T22:00",
        "risk": 0.0
      },
      {
        "time": "2026-05-29T23:00",
        "risk": 0.0
      }
    ]
  },
  {
    "lat": 51.2,
    "lon": 24.0,
    "risk": 0.0,
    "alert": false,
    "ndvi_stress": 0.48,
    "elevation_m": 179.0,
    "slope_deg": 0.2,
    "shap_drivers": [
      {
        "feature": "wind_dryness_ratio",
        "shap": 0.0
      },
      {
        "feature": "dryness_ratio",
        "shap": 0.0
      },
      {
        "feature": "soil_x_rh",
        "shap": 0.0
      }
    ],
    "hourly_risk": [
      {
        "time": "2026-05-29T00:00",
        "risk": 0.0
      },
      {
        "time": "2026-05-29T01:00",
        "risk": 0.0
      },
      {
        "time": "2026-05-29T02:00",
        "risk": 0.0
      },
      {
        "time": "2026-05-29T03:00",
        "risk": 0.0
      },
      {
        "time": "2026-05-29T04:00",
        "risk": 0.0
      },
      {
        "time": "2026-05-29T05:00",
        "risk": 0.0
      },
      {
        "time": "2026-05-29T06:00",
        "risk": 0.0
      },
      {
        "time": "2026-05-29T07:00",
        "risk": 0.0
      },
      {
        "time": "2026-05-29T08:00",
        "risk": 0.0
      },
      {
        "time": "2026-05-29T09:00",
        "risk": 0.0
      },
      {
        "time": "2026-05-29T10:00",
        "risk": 0.0
      },
      {
        "time": "2026-05-29T11:00",
        "risk": 0.0
      },
      {
        "time": "2026-05-29T12:00",
        "risk": 0.0
      },
      {
        "time": "2026-05-29T13:00",
        "risk": 0.0
      },
      {
        "time": "2026-05-29T14:00",
        "risk": 0.0
      },
      {
        "time": "2026-05-29T15:00",
        "risk": 0.0
      },
      {
        "time": "2026-05-29T16:00",
        "risk": 0.0
      },
      {
        "time": "2026-05-29T17:00",
        "risk": 0.0
      },
      {
        "time": "2026-05-29T18:00",
        "risk": 0.0
      },
      {
        "time": "2026-05-29T19:00",
        "risk": 0.0
      },
      {
        "time": "2026-05-29T20:00",
        "risk": 0.0
      },
      {
        "time": "2026-05-29T21:00",
        "risk": 0.0
      },
      {
        "time": "2026-05-29T22:00",
        "risk": 0.0
      },
      {
        "time": "2026-05-29T23:00",
        "risk": 0.0
      }
    ]
  },
  {
    "lat": 52.3,
    "lon": 16.0,
    "risk": 0.0,
    "alert": false,
    "ndvi_stress": 0.619,
    "elevation_m": 78.0,
    "slope_deg": 0.07,
    "shap_drivers": [
      {
        "feature": "wind_dryness_ratio",
        "shap": 0.0
      },
      {
        "feature": "dryness_ratio",
        "shap": 0.0
      },
      {
        "feature": "soil_x_rh",
        "shap": 0.0
      }
    ],
    "hourly_risk": [
      {
        "time": "2026-05-29T00:00",
        "risk": 0.0
      },
      {
        "time": "2026-05-29T01:00",
        "risk": 0.0
      },
      {
        "time": "2026-05-29T02:00",
        "risk": 0.0
      },
      {
        "time": "2026-05-29T03:00",
        "risk": 0.0
      },
      {
        "time": "2026-05-29T04:00",
        "risk": 0.0
      },
      {
        "time": "2026-05-29T05:00",
        "risk": 0.0
      },
      {
        "time": "2026-05-29T06:00",
        "risk": 0.0
      },
      {
        "time": "2026-05-29T07:00",
        "risk": 0.0
      },
      {
        "time": "2026-05-29T08:00",
        "risk": 0.0
      },
      {
        "time": "2026-05-29T09:00",
        "risk": 0.0
      },
      {
        "time": "2026-05-29T10:00",
        "risk": 0.0
      },
      {
        "time": "2026-05-29T11:00",
        "risk": 0.0
      },
      {
        "time": "2026-05-29T12:00",
        "risk": 0.0
      },
      {
        "time": "2026-05-29T13:00",
        "risk": 0.0
      },
      {
        "time": "2026-05-29T14:00",
        "risk": 0.0
      },
      {
        "time": "2026-05-29T15:00",
        "risk": 0.0
      },
      {
        "time": "2026-05-29T16:00",
        "risk": 0.0
      },
      {
        "time": "2026-05-29T17:00",
        "risk": 0.0
      },
      {
        "time": "2026-05-29T18:00",
        "risk": 0.0
      },
      {
        "time": "2026-05-29T19:00",
        "risk": 0.0
      },
      {
        "time": "2026-05-29T20:00",
        "risk": 0.0
      },
      {
        "time": "2026-05-29T21:00",
        "risk": 0.0
      },
      {
        "time": "2026-05-29T22:00",
        "risk": 0.0
      },
      {
        "time": "2026-05-29T23:00",
        "risk": 0.0
      }
    ]
  },
  {
    "lat": 52.3,
    "lon": 18.0,
    "risk": 0.0,
    "alert": false,
    "ndvi_stress": 0.558,
    "elevation_m": 98.0,
    "slope_deg": 0.05,
    "shap_drivers": [
      {
        "feature": "wind_dryness_ratio",
        "shap": 0.0
      },
      {
        "feature": "dryness_ratio",
        "shap": 0.0
      },
      {
        "feature": "soil_x_rh",
        "shap": 0.0
      }
    ],
    "hourly_risk": [
      {
        "time": "2026-05-29T00:00",
        "risk": 0.0
      },
      {
        "time": "2026-05-29T01:00",
        "risk": 0.0
      },
      {
        "time": "2026-05-29T02:00",
        "risk": 0.0
      },
      {
        "time": "2026-05-29T03:00",
        "risk": 0.0
      },
      {
        "time": "2026-05-29T04:00",
        "risk": 0.0
      },
      {
        "time": "2026-05-29T05:00",
        "risk": 0.0
      },
      {
        "time": "2026-05-29T06:00",
        "risk": 0.0
      },
      {
        "time": "2026-05-29T07:00",
        "risk": 0.0
      },
      {
        "time": "2026-05-29T08:00",
        "risk": 0.0
      },
      {
        "time": "2026-05-29T09:00",
        "risk": 0.0
      },
      {
        "time": "2026-05-29T10:00",
        "risk": 0.0
      },
      {
        "time": "2026-05-29T11:00",
        "risk": 0.0
      },
      {
        "time": "2026-05-29T12:00",
        "risk": 0.0
      },
      {
        "time": "2026-05-29T13:00",
        "risk": 0.0
      },
      {
        "time": "2026-05-29T14:00",
        "risk": 0.0
      },
      {
        "time": "2026-05-29T15:00",
        "risk": 0.0
      },
      {
        "time": "2026-05-29T16:00",
        "risk": 0.0
      },
      {
        "time": "2026-05-29T17:00",
        "risk": 0.0
      },
      {
        "time": "2026-05-29T18:00",
        "risk": 0.0
      },
      {
        "time": "2026-05-29T19:00",
        "risk": 0.0
      },
      {
        "time": "2026-05-29T20:00",
        "risk": 0.0
      },
      {
        "time": "2026-05-29T21:00",
        "risk": 0.0
      },
      {
        "time": "2026-05-29T22:00",
        "risk": 0.0
      },
      {
        "time": "2026-05-29T23:00",
        "risk": 0.0
      }
    ]
  },
  {
    "lat": 52.3,
    "lon": 20.0,
    "risk": 0.0,
    "alert": false,
    "ndvi_stress": 0.459,
    "elevation_m": 98.0,
    "slope_deg": 0.19,
    "shap_drivers": [
      {
        "feature": "wind_dryness_ratio",
        "shap": 0.0
      },
      {
        "feature": "dryness_ratio",
        "shap": 0.0
      },
      {
        "feature": "soil_x_rh",
        "shap": 0.0
      }
    ],
    "hourly_risk": [
      {
        "time": "2026-05-29T00:00",
        "risk": 0.0
      },
      {
        "time": "2026-05-29T01:00",
        "risk": 0.0
      },
      {
        "time": "2026-05-29T02:00",
        "risk": 0.0
      },
      {
        "time": "2026-05-29T03:00",
        "risk": 0.0
      },
      {
        "time": "2026-05-29T04:00",
        "risk": 0.0
      },
      {
        "time": "2026-05-29T05:00",
        "risk": 0.0
      },
      {
        "time": "2026-05-29T06:00",
        "risk": 0.0
      },
      {
        "time": "2026-05-29T07:00",
        "risk": 0.0
      },
      {
        "time": "2026-05-29T08:00",
        "risk": 0.0
      },
      {
        "time": "2026-05-29T09:00",
        "risk": 0.0
      },
      {
        "time": "2026-05-29T10:00",
        "risk": 0.0
      },
      {
        "time": "2026-05-29T11:00",
        "risk": 0.0
      },
      {
        "time": "2026-05-29T12:00",
        "risk": 0.0
      },
      {
        "time": "2026-05-29T13:00",
        "risk": 0.0
      },
      {
        "time": "2026-05-29T14:00",
        "risk": 0.0
      },
      {
        "time": "2026-05-29T15:00",
        "risk": 0.0
      },
      {
        "time": "2026-05-29T16:00",
        "risk": 0.0
      },
      {
        "time": "2026-05-29T17:00",
        "risk": 0.0
      },
      {
        "time": "2026-05-29T18:00",
        "risk": 0.0
      },
      {
        "time": "2026-05-29T19:00",
        "risk": 0.0
      },
      {
        "time": "2026-05-29T20:00",
        "risk": 0.0
      },
      {
        "time": "2026-05-29T21:00",
        "risk": 0.0
      },
      {
        "time": "2026-05-29T22:00",
        "risk": 0.0
      },
      {
        "time": "2026-05-29T23:00",
        "risk": 0.0
      }
    ]
  },
  {
    "lat": 52.3,
    "lon": 22.0,
    "risk": 0.0,
    "alert": false,
    "ndvi_stress": 0.497,
    "elevation_m": 123.0,
    "slope_deg": 0.27,
    "shap_drivers": [
      {
        "feature": "wind_dryness_ratio",
        "shap": 0.0
      },
      {
        "feature": "dryness_ratio",
        "shap": 0.0
      },
      {
        "feature": "soil_x_rh",
        "shap": 0.0
      }
    ],
    "hourly_risk": [
      {
        "time": "2026-05-29T00:00",
        "risk": 0.0
      },
      {
        "time": "2026-05-29T01:00",
        "risk": 0.0
      },
      {
        "time": "2026-05-29T02:00",
        "risk": 0.0
      },
      {
        "time": "2026-05-29T03:00",
        "risk": 0.0
      },
      {
        "time": "2026-05-29T04:00",
        "risk": 0.0
      },
      {
        "time": "2026-05-29T05:00",
        "risk": 0.0
      },
      {
        "time": "2026-05-29T06:00",
        "risk": 0.0
      },
      {
        "time": "2026-05-29T07:00",
        "risk": 0.0
      },
      {
        "time": "2026-05-29T08:00",
        "risk": 0.0
      },
      {
        "time": "2026-05-29T09:00",
        "risk": 0.0
      },
      {
        "time": "2026-05-29T10:00",
        "risk": 0.0
      },
      {
        "time": "2026-05-29T11:00",
        "risk": 0.0
      },
      {
        "time": "2026-05-29T12:00",
        "risk": 0.0
      },
      {
        "time": "2026-05-29T13:00",
        "risk": 0.0
      },
      {
        "time": "2026-05-29T14:00",
        "risk": 0.0
      },
      {
        "time": "2026-05-29T15:00",
        "risk": 0.0
      },
      {
        "time": "2026-05-29T16:00",
        "risk": 0.0
      },
      {
        "time": "2026-05-29T17:00",
        "risk": 0.0
      },
      {
        "time": "2026-05-29T18:00",
        "risk": 0.0
      },
      {
        "time": "2026-05-29T19:00",
        "risk": 0.0
      },
      {
        "time": "2026-05-29T20:00",
        "risk": 0.0
      },
      {
        "time": "2026-05-29T21:00",
        "risk": 0.0
      },
      {
        "time": "2026-05-29T22:00",
        "risk": 0.0
      },
      {
        "time": "2026-05-29T23:00",
        "risk": 0.0
      }
    ]
  },
  {
    "lat": 53.4,
    "lon": 14.0,
    "risk": 0.0,
    "alert": false,
    "ndvi_stress": 0.394,
    "elevation_m": 49.0,
    "slope_deg": 0.1,
    "shap_drivers": [
      {
        "feature": "wind_dryness_ratio",
        "shap": 0.0
      },
      {
        "feature": "dryness_ratio",
        "shap": 0.0
      },
      {
        "feature": "soil_x_rh",
        "shap": 0.0
      }
    ],
    "hourly_risk": [
      {
        "time": "2026-05-29T00:00",
        "risk": 0.0
      },
      {
        "time": "2026-05-29T01:00",
        "risk": 0.0
      },
      {
        "time": "2026-05-29T02:00",
        "risk": 0.0
      },
      {
        "time": "2026-05-29T03:00",
        "risk": 0.0
      },
      {
        "time": "2026-05-29T04:00",
        "risk": 0.0
      },
      {
        "time": "2026-05-29T05:00",
        "risk": 0.0
      },
      {
        "time": "2026-05-29T06:00",
        "risk": 0.0
      },
      {
        "time": "2026-05-29T07:00",
        "risk": 0.0
      },
      {
        "time": "2026-05-29T08:00",
        "risk": 0.0
      },
      {
        "time": "2026-05-29T09:00",
        "risk": 0.0
      },
      {
        "time": "2026-05-29T10:00",
        "risk": 0.0
      },
      {
        "time": "2026-05-29T11:00",
        "risk": 0.0
      },
      {
        "time": "2026-05-29T12:00",
        "risk": 0.0
      },
      {
        "time": "2026-05-29T13:00",
        "risk": 0.0
      },
      {
        "time": "2026-05-29T14:00",
        "risk": 0.0
      },
      {
        "time": "2026-05-29T15:00",
        "risk": 0.0
      },
      {
        "time": "2026-05-29T16:00",
        "risk": 0.0
      },
      {
        "time": "2026-05-29T17:00",
        "risk": 0.0
      },
      {
        "time": "2026-05-29T18:00",
        "risk": 0.0
      },
      {
        "time": "2026-05-29T19:00",
        "risk": 0.0
      },
      {
        "time": "2026-05-29T20:00",
        "risk": 0.0
      },
      {
        "time": "2026-05-29T21:00",
        "risk": 0.0
      },
      {
        "time": "2026-05-29T22:00",
        "risk": 0.0
      },
      {
        "time": "2026-05-29T23:00",
        "risk": 0.0
      }
    ]
  },
  {
    "lat": 52.3,
    "lon": 24.0,
    "risk": 0.0,
    "alert": false,
    "ndvi_stress": 0.459,
    "elevation_m": 148.0,
    "slope_deg": 0.03,
    "shap_drivers": [
      {
        "feature": "wind_dryness_ratio",
        "shap": 0.0
      },
      {
        "feature": "dryness_ratio",
        "shap": 0.0
      },
      {
        "feature": "soil_x_rh",
        "shap": 0.0
      }
    ],
    "hourly_risk": [
      {
        "time": "2026-05-29T00:00",
        "risk": 0.0
      },
      {
        "time": "2026-05-29T01:00",
        "risk": 0.0
      },
      {
        "time": "2026-05-29T02:00",
        "risk": 0.0
      },
      {
        "time": "2026-05-29T03:00",
        "risk": 0.0
      },
      {
        "time": "2026-05-29T04:00",
        "risk": 0.0
      },
      {
        "time": "2026-05-29T05:00",
        "risk": 0.0
      },
      {
        "time": "2026-05-29T06:00",
        "risk": 0.0
      },
      {
        "time": "2026-05-29T07:00",
        "risk": 0.0
      },
      {
        "time": "2026-05-29T08:00",
        "risk": 0.0
      },
      {
        "time": "2026-05-29T09:00",
        "risk": 0.0
      },
      {
        "time": "2026-05-29T10:00",
        "risk": 0.0
      },
      {
        "time": "2026-05-29T11:00",
        "risk": 0.0
      },
      {
        "time": "2026-05-29T12:00",
        "risk": 0.0
      },
      {
        "time": "2026-05-29T13:00",
        "risk": 0.0
      },
      {
        "time": "2026-05-29T14:00",
        "risk": 0.0
      },
      {
        "time": "2026-05-29T15:00",
        "risk": 0.0
      },
      {
        "time": "2026-05-29T16:00",
        "risk": 0.0
      },
      {
        "time": "2026-05-29T17:00",
        "risk": 0.0
      },
      {
        "time": "2026-05-29T18:00",
        "risk": 0.0
      },
      {
        "time": "2026-05-29T19:00",
        "risk": 0.0
      },
      {
        "time": "2026-05-29T20:00",
        "risk": 0.0
      },
      {
        "time": "2026-05-29T21:00",
        "risk": 0.0
      },
      {
        "time": "2026-05-29T22:00",
        "risk": 0.0
      },
      {
        "time": "2026-05-29T23:00",
        "risk": 0.0
      }
    ]
  },
  {
    "lat": 53.4,
    "lon": 18.0,
    "risk": 0.0,
    "alert": false,
    "ndvi_stress": 0.58,
    "elevation_m": 91.0,
    "slope_deg": 0.08,
    "shap_drivers": [
      {
        "feature": "wind_dryness_ratio",
        "shap": 0.0
      },
      {
        "feature": "dryness_ratio",
        "shap": 0.0
      },
      {
        "feature": "soil_x_rh",
        "shap": 0.0
      }
    ],
    "hourly_risk": [
      {
        "time": "2026-05-29T00:00",
        "risk": 0.0
      },
      {
        "time": "2026-05-29T01:00",
        "risk": 0.0
      },
      {
        "time": "2026-05-29T02:00",
        "risk": 0.0
      },
      {
        "time": "2026-05-29T03:00",
        "risk": 0.0
      },
      {
        "time": "2026-05-29T04:00",
        "risk": 0.0
      },
      {
        "time": "2026-05-29T05:00",
        "risk": 0.0
      },
      {
        "time": "2026-05-29T06:00",
        "risk": 0.0
      },
      {
        "time": "2026-05-29T07:00",
        "risk": 0.0
      },
      {
        "time": "2026-05-29T08:00",
        "risk": 0.0
      },
      {
        "time": "2026-05-29T09:00",
        "risk": 0.0
      },
      {
        "time": "2026-05-29T10:00",
        "risk": 0.0
      },
      {
        "time": "2026-05-29T11:00",
        "risk": 0.0
      },
      {
        "time": "2026-05-29T12:00",
        "risk": 0.0
      },
      {
        "time": "2026-05-29T13:00",
        "risk": 0.0
      },
      {
        "time": "2026-05-29T14:00",
        "risk": 0.0
      },
      {
        "time": "2026-05-29T15:00",
        "risk": 0.0
      },
      {
        "time": "2026-05-29T16:00",
        "risk": 0.0
      },
      {
        "time": "2026-05-29T17:00",
        "risk": 0.0
      },
      {
        "time": "2026-05-29T18:00",
        "risk": 0.0
      },
      {
        "time": "2026-05-29T19:00",
        "risk": 0.0
      },
      {
        "time": "2026-05-29T20:00",
        "risk": 0.0
      },
      {
        "time": "2026-05-29T21:00",
        "risk": 0.0
      },
      {
        "time": "2026-05-29T22:00",
        "risk": 0.0
      },
      {
        "time": "2026-05-29T23:00",
        "risk": 0.0
      }
    ]
  },
  {
    "lat": 53.4,
    "lon": 16.0,
    "risk": 0.0,
    "alert": false,
    "ndvi_stress": 0.552,
    "elevation_m": 140.0,
    "slope_deg": 0.05,
    "shap_drivers": [
      {
        "feature": "wind_dryness_ratio",
        "shap": 0.0
      },
      {
        "feature": "dryness_ratio",
        "shap": 0.0
      },
      {
        "feature": "soil_x_rh",
        "shap": 0.0
      }
    ],
    "hourly_risk": [
      {
        "time": "2026-05-29T00:00",
        "risk": 0.0
      },
      {
        "time": "2026-05-29T01:00",
        "risk": 0.0
      },
      {
        "time": "2026-05-29T02:00",
        "risk": 0.0
      },
      {
        "time": "2026-05-29T03:00",
        "risk": 0.0
      },
      {
        "time": "2026-05-29T04:00",
        "risk": 0.0
      },
      {
        "time": "2026-05-29T05:00",
        "risk": 0.0
      },
      {
        "time": "2026-05-29T06:00",
        "risk": 0.0
      },
      {
        "time": "2026-05-29T07:00",
        "risk": 0.0
      },
      {
        "time": "2026-05-29T08:00",
        "risk": 0.0
      },
      {
        "time": "2026-05-29T09:00",
        "risk": 0.0
      },
      {
        "time": "2026-05-29T10:00",
        "risk": 0.0
      },
      {
        "time": "2026-05-29T11:00",
        "risk": 0.0
      },
      {
        "time": "2026-05-29T12:00",
        "risk": 0.0
      },
      {
        "time": "2026-05-29T13:00",
        "risk": 0.0
      },
      {
        "time": "2026-05-29T14:00",
        "risk": 0.0
      },
      {
        "time": "2026-05-29T15:00",
        "risk": 0.0
      },
      {
        "time": "2026-05-29T16:00",
        "risk": 0.0
      },
      {
        "time": "2026-05-29T17:00",
        "risk": 0.0
      },
      {
        "time": "2026-05-29T18:00",
        "risk": 0.0
      },
      {
        "time": "2026-05-29T19:00",
        "risk": 0.0
      },
      {
        "time": "2026-05-29T20:00",
        "risk": 0.0
      },
      {
        "time": "2026-05-29T21:00",
        "risk": 0.0
      },
      {
        "time": "2026-05-29T22:00",
        "risk": 0.0
      },
      {
        "time": "2026-05-29T23:00",
        "risk": 0.0
      }
    ]
  },
  {
    "lat": 53.4,
    "lon": 20.0,
    "risk": 0.0,
    "alert": false,
    "ndvi_stress": 0.39,
    "elevation_m": 182.0,
    "slope_deg": 0.1,
    "shap_drivers": [
      {
        "feature": "wind_dryness_ratio",
        "shap": 0.0
      },
      {
        "feature": "dryness_ratio",
        "shap": 0.0
      },
      {
        "feature": "soil_x_rh",
        "shap": 0.0
      }
    ],
    "hourly_risk": [
      {
        "time": "2026-05-29T00:00",
        "risk": 0.0
      },
      {
        "time": "2026-05-29T01:00",
        "risk": 0.0
      },
      {
        "time": "2026-05-29T02:00",
        "risk": 0.0
      },
      {
        "time": "2026-05-29T03:00",
        "risk": 0.0
      },
      {
        "time": "2026-05-29T04:00",
        "risk": 0.0
      },
      {
        "time": "2026-05-29T05:00",
        "risk": 0.0
      },
      {
        "time": "2026-05-29T06:00",
        "risk": 0.0
      },
      {
        "time": "2026-05-29T07:00",
        "risk": 0.0
      },
      {
        "time": "2026-05-29T08:00",
        "risk": 0.0
      },
      {
        "time": "2026-05-29T09:00",
        "risk": 0.0
      },
      {
        "time": "2026-05-29T10:00",
        "risk": 0.0
      },
      {
        "time": "2026-05-29T11:00",
        "risk": 0.0
      },
      {
        "time": "2026-05-29T12:00",
        "risk": 0.0
      },
      {
        "time": "2026-05-29T13:00",
        "risk": 0.0
      },
      {
        "time": "2026-05-29T14:00",
        "risk": 0.0
      },
      {
        "time": "2026-05-29T15:00",
        "risk": 0.0
      },
      {
        "time": "2026-05-29T16:00",
        "risk": 0.0
      },
      {
        "time": "2026-05-29T17:00",
        "risk": 0.0
      },
      {
        "time": "2026-05-29T18:00",
        "risk": 0.0
      },
      {
        "time": "2026-05-29T19:00",
        "risk": 0.0
      },
      {
        "time": "2026-05-29T20:00",
        "risk": 0.0
      },
      {
        "time": "2026-05-29T21:00",
        "risk": 0.0
      },
      {
        "time": "2026-05-29T22:00",
        "risk": 0.0
      },
      {
        "time": "2026-05-29T23:00",
        "risk": 0.0
      }
    ]
  },
  {
    "lat": 53.4,
    "lon": 22.0,
    "risk": 0.0,
    "alert": false,
    "ndvi_stress": 0.454,
    "elevation_m": 141.0,
    "slope_deg": 0.16,
    "shap_drivers": [
      {
        "feature": "wind_dryness_ratio",
        "shap": 0.0
      },
      {
        "feature": "dryness_ratio",
        "shap": 0.0
      },
      {
        "feature": "soil_x_rh",
        "shap": 0.0
      }
    ],
    "hourly_risk": [
      {
        "time": "2026-05-29T00:00",
        "risk": 0.0
      },
      {
        "time": "2026-05-29T01:00",
        "risk": 0.0
      },
      {
        "time": "2026-05-29T02:00",
        "risk": 0.0
      },
      {
        "time": "2026-05-29T03:00",
        "risk": 0.0
      },
      {
        "time": "2026-05-29T04:00",
        "risk": 0.0
      },
      {
        "time": "2026-05-29T05:00",
        "risk": 0.0
      },
      {
        "time": "2026-05-29T06:00",
        "risk": 0.0
      },
      {
        "time": "2026-05-29T07:00",
        "risk": 0.0
      },
      {
        "time": "2026-05-29T08:00",
        "risk": 0.0
      },
      {
        "time": "2026-05-29T09:00",
        "risk": 0.0
      },
      {
        "time": "2026-05-29T10:00",
        "risk": 0.0
      },
      {
        "time": "2026-05-29T11:00",
        "risk": 0.0
      },
      {
        "time": "2026-05-29T12:00",
        "risk": 0.0
      },
      {
        "time": "2026-05-29T13:00",
        "risk": 0.0
      },
      {
        "time": "2026-05-29T14:00",
        "risk": 0.0
      },
      {
        "time": "2026-05-29T15:00",
        "risk": 0.0
      },
      {
        "time": "2026-05-29T16:00",
        "risk": 0.0
      },
      {
        "time": "2026-05-29T17:00",
        "risk": 0.0
      },
      {
        "time": "2026-05-29T18:00",
        "risk": 0.0
      },
      {
        "time": "2026-05-29T19:00",
        "risk": 0.0
      },
      {
        "time": "2026-05-29T20:00",
        "risk": 0.0
      },
      {
        "time": "2026-05-29T21:00",
        "risk": 0.0
      },
      {
        "time": "2026-05-29T22:00",
        "risk": 0.0
      },
      {
        "time": "2026-05-29T23:00",
        "risk": 0.0
      }
    ]
  },
  {
    "lat": 53.4,
    "lon": 24.0,
    "risk": 0.0,
    "alert": false,
    "ndvi_stress": 0.382,
    "elevation_m": 115.0,
    "slope_deg": 0.1,
    "shap_drivers": [
      {
        "feature": "wind_dryness_ratio",
        "shap": 0.0
      },
      {
        "feature": "dryness_ratio",
        "shap": 0.0
      },
      {
        "feature": "soil_x_rh",
        "shap": 0.0
      }
    ],
    "hourly_risk": [
      {
        "time": "2026-05-29T00:00",
        "risk": 0.0
      },
      {
        "time": "2026-05-29T01:00",
        "risk": 0.0
      },
      {
        "time": "2026-05-29T02:00",
        "risk": 0.0
      },
      {
        "time": "2026-05-29T03:00",
        "risk": 0.0
      },
      {
        "time": "2026-05-29T04:00",
        "risk": 0.0
      },
      {
        "time": "2026-05-29T05:00",
        "risk": 0.0
      },
      {
        "time": "2026-05-29T06:00",
        "risk": 0.0
      },
      {
        "time": "2026-05-29T07:00",
        "risk": 0.0
      },
      {
        "time": "2026-05-29T08:00",
        "risk": 0.0
      },
      {
        "time": "2026-05-29T09:00",
        "risk": 0.0
      },
      {
        "time": "2026-05-29T10:00",
        "risk": 0.0
      },
      {
        "time": "2026-05-29T11:00",
        "risk": 0.0
      },
      {
        "time": "2026-05-29T12:00",
        "risk": 0.0
      },
      {
        "time": "2026-05-29T13:00",
        "risk": 0.0
      },
      {
        "time": "2026-05-29T14:00",
        "risk": 0.0
      },
      {
        "time": "2026-05-29T15:00",
        "risk": 0.0
      },
      {
        "time": "2026-05-29T16:00",
        "risk": 0.0
      },
      {
        "time": "2026-05-29T17:00",
        "risk": 0.0
      },
      {
        "time": "2026-05-29T18:00",
        "risk": 0.0
      },
      {
        "time": "2026-05-29T19:00",
        "risk": 0.0
      },
      {
        "time": "2026-05-29T20:00",
        "risk": 0.0
      },
      {
        "time": "2026-05-29T21:00",
        "risk": 0.0
      },
      {
        "time": "2026-05-29T22:00",
        "risk": 0.0
      },
      {
        "time": "2026-05-29T23:00",
        "risk": 0.0
      }
    ]
  },
  {
    "lat": 54.5,
    "lon": 14.0,
    "risk": 0.0,
    "alert": false,
    "ndvi_stress": 0.482,
    "elevation_m": 0.0,
    "slope_deg": 0.0,
    "shap_drivers": [
      {
        "feature": "wind_dryness_ratio",
        "shap": 0.0
      },
      {
        "feature": "dryness_ratio",
        "shap": 0.0
      },
      {
        "feature": "soil_x_rh",
        "shap": 0.0
      }
    ],
    "hourly_risk": [
      {
        "time": "2026-05-29T00:00",
        "risk": 0.0
      },
      {
        "time": "2026-05-29T01:00",
        "risk": 0.0
      },
      {
        "time": "2026-05-29T02:00",
        "risk": 0.0
      },
      {
        "time": "2026-05-29T03:00",
        "risk": 0.0
      },
      {
        "time": "2026-05-29T04:00",
        "risk": 0.0
      },
      {
        "time": "2026-05-29T05:00",
        "risk": 0.0
      },
      {
        "time": "2026-05-29T06:00",
        "risk": 0.0
      },
      {
        "time": "2026-05-29T07:00",
        "risk": 0.0
      },
      {
        "time": "2026-05-29T08:00",
        "risk": 0.0
      },
      {
        "time": "2026-05-29T09:00",
        "risk": 0.0
      },
      {
        "time": "2026-05-29T10:00",
        "risk": 0.0
      },
      {
        "time": "2026-05-29T11:00",
        "risk": 0.0
      },
      {
        "time": "2026-05-29T12:00",
        "risk": 0.0
      },
      {
        "time": "2026-05-29T13:00",
        "risk": 0.0
      },
      {
        "time": "2026-05-29T14:00",
        "risk": 0.0
      },
      {
        "time": "2026-05-29T15:00",
        "risk": 0.0
      },
      {
        "time": "2026-05-29T16:00",
        "risk": 0.0
      },
      {
        "time": "2026-05-29T17:00",
        "risk": 0.0
      },
      {
        "time": "2026-05-29T18:00",
        "risk": 0.0
      },
      {
        "time": "2026-05-29T19:00",
        "risk": 0.0
      },
      {
        "time": "2026-05-29T20:00",
        "risk": 0.0
      },
      {
        "time": "2026-05-29T21:00",
        "risk": 0.0
      },
      {
        "time": "2026-05-29T22:00",
        "risk": 0.0
      },
      {
        "time": "2026-05-29T23:00",
        "risk": 0.0
      }
    ]
  },
  {
    "lat": 54.5,
    "lon": 18.0,
    "risk": 0.0,
    "alert": false,
    "ndvi_stress": 0.444,
    "elevation_m": 109.0,
    "slope_deg": 0.22,
    "shap_drivers": [
      {
        "feature": "wind_dryness_ratio",
        "shap": 0.0
      },
      {
        "feature": "dryness_ratio",
        "shap": 0.0
      },
      {
        "feature": "soil_x_rh",
        "shap": 0.0
      }
    ],
    "hourly_risk": [
      {
        "time": "2026-05-29T00:00",
        "risk": 0.0
      },
      {
        "time": "2026-05-29T01:00",
        "risk": 0.0
      },
      {
        "time": "2026-05-29T02:00",
        "risk": 0.0
      },
      {
        "time": "2026-05-29T03:00",
        "risk": 0.0
      },
      {
        "time": "2026-05-29T04:00",
        "risk": 0.0
      },
      {
        "time": "2026-05-29T05:00",
        "risk": 0.0
      },
      {
        "time": "2026-05-29T06:00",
        "risk": 0.0
      },
      {
        "time": "2026-05-29T07:00",
        "risk": 0.0
      },
      {
        "time": "2026-05-29T08:00",
        "risk": 0.0
      },
      {
        "time": "2026-05-29T09:00",
        "risk": 0.0
      },
      {
        "time": "2026-05-29T10:00",
        "risk": 0.0
      },
      {
        "time": "2026-05-29T11:00",
        "risk": 0.0
      },
      {
        "time": "2026-05-29T12:00",
        "risk": 0.0
      },
      {
        "time": "2026-05-29T13:00",
        "risk": 0.0
      },
      {
        "time": "2026-05-29T14:00",
        "risk": 0.0
      },
      {
        "time": "2026-05-29T15:00",
        "risk": 0.0
      },
      {
        "time": "2026-05-29T16:00",
        "risk": 0.0
      },
      {
        "time": "2026-05-29T17:00",
        "risk": 0.0
      },
      {
        "time": "2026-05-29T18:00",
        "risk": 0.0
      },
      {
        "time": "2026-05-29T19:00",
        "risk": 0.0
      },
      {
        "time": "2026-05-29T20:00",
        "risk": 0.0
      },
      {
        "time": "2026-05-29T21:00",
        "risk": 0.0
      },
      {
        "time": "2026-05-29T22:00",
        "risk": 0.0
      },
      {
        "time": "2026-05-29T23:00",
        "risk": 0.0
      }
    ]
  },
  {
    "lat": 54.5,
    "lon": 16.0,
    "risk": 0.0,
    "alert": false,
    "ndvi_stress": 0.449,
    "elevation_m": 0.0,
    "slope_deg": 0.0,
    "shap_drivers": [
      {
        "feature": "wind_dryness_ratio",
        "shap": 0.0
      },
      {
        "feature": "dryness_ratio",
        "shap": 0.0
      },
      {
        "feature": "soil_x_rh",
        "shap": 0.0
      }
    ],
    "hourly_risk": [
      {
        "time": "2026-05-29T00:00",
        "risk": 0.0
      },
      {
        "time": "2026-05-29T01:00",
        "risk": 0.0
      },
      {
        "time": "2026-05-29T02:00",
        "risk": 0.0
      },
      {
        "time": "2026-05-29T03:00",
        "risk": 0.0
      },
      {
        "time": "2026-05-29T04:00",
        "risk": 0.0
      },
      {
        "time": "2026-05-29T05:00",
        "risk": 0.0
      },
      {
        "time": "2026-05-29T06:00",
        "risk": 0.0
      },
      {
        "time": "2026-05-29T07:00",
        "risk": 0.0
      },
      {
        "time": "2026-05-29T08:00",
        "risk": 0.0
      },
      {
        "time": "2026-05-29T09:00",
        "risk": 0.0
      },
      {
        "time": "2026-05-29T10:00",
        "risk": 0.0
      },
      {
        "time": "2026-05-29T11:00",
        "risk": 0.0
      },
      {
        "time": "2026-05-29T12:00",
        "risk": 0.0
      },
      {
        "time": "2026-05-29T13:00",
        "risk": 0.0
      },
      {
        "time": "2026-05-29T14:00",
        "risk": 0.0
      },
      {
        "time": "2026-05-29T15:00",
        "risk": 0.0
      },
      {
        "time": "2026-05-29T16:00",
        "risk": 0.0
      },
      {
        "time": "2026-05-29T17:00",
        "risk": 0.0
      },
      {
        "time": "2026-05-29T18:00",
        "risk": 0.0
      },
      {
        "time": "2026-05-29T19:00",
        "risk": 0.0
      },
      {
        "time": "2026-05-29T20:00",
        "risk": 0.0
      },
      {
        "time": "2026-05-29T21:00",
        "risk": 0.0
      },
      {
        "time": "2026-05-29T22:00",
        "risk": 0.0
      },
      {
        "time": "2026-05-29T23:00",
        "risk": 0.0
      }
    ]
  },
  {
    "lat": 54.5,
    "lon": 22.0,
    "risk": 0.0,
    "alert": false,
    "ndvi_stress": 0.343,
    "elevation_m": 76.0,
    "slope_deg": 0.26,
    "shap_drivers": [
      {
        "feature": "wind_dryness_ratio",
        "shap": 0.0
      },
      {
        "feature": "dryness_ratio",
        "shap": 0.0
      },
      {
        "feature": "soil_x_rh",
        "shap": 0.0
      }
    ],
    "hourly_risk": [
      {
        "time": "2026-05-29T00:00",
        "risk": 0.0
      },
      {
        "time": "2026-05-29T01:00",
        "risk": 0.0
      },
      {
        "time": "2026-05-29T02:00",
        "risk": 0.0
      },
      {
        "time": "2026-05-29T03:00",
        "risk": 0.0
      },
      {
        "time": "2026-05-29T04:00",
        "risk": 0.0
      },
      {
        "time": "2026-05-29T05:00",
        "risk": 0.0
      },
      {
        "time": "2026-05-29T06:00",
        "risk": 0.0
      },
      {
        "time": "2026-05-29T07:00",
        "risk": 0.0
      },
      {
        "time": "2026-05-29T08:00",
        "risk": 0.0
      },
      {
        "time": "2026-05-29T09:00",
        "risk": 0.0
      },
      {
        "time": "2026-05-29T10:00",
        "risk": 0.0
      },
      {
        "time": "2026-05-29T11:00",
        "risk": 0.0
      },
      {
        "time": "2026-05-29T12:00",
        "risk": 0.0
      },
      {
        "time": "2026-05-29T13:00",
        "risk": 0.0
      },
      {
        "time": "2026-05-29T14:00",
        "risk": 0.0
      },
      {
        "time": "2026-05-29T15:00",
        "risk": 0.0
      },
      {
        "time": "2026-05-29T16:00",
        "risk": 0.0
      },
      {
        "time": "2026-05-29T17:00",
        "risk": 0.0
      },
      {
        "time": "2026-05-29T18:00",
        "risk": 0.0
      },
      {
        "time": "2026-05-29T19:00",
        "risk": 0.0
      },
      {
        "time": "2026-05-29T20:00",
        "risk": 0.0
      },
      {
        "time": "2026-05-29T21:00",
        "risk": 0.0
      },
      {
        "time": "2026-05-29T22:00",
        "risk": 0.0
      },
      {
        "time": "2026-05-29T23:00",
        "risk": 0.0
      }
    ]
  },
  {
    "lat": 54.5,
    "lon": 24.0,
    "risk": 0.0,
    "alert": false,
    "ndvi_stress": 0.377,
    "elevation_m": 80.0,
    "slope_deg": 0.23,
    "shap_drivers": [
      {
        "feature": "wind_dryness_ratio",
        "shap": 0.0
      },
      {
        "feature": "dryness_ratio",
        "shap": 0.0
      },
      {
        "feature": "soil_x_rh",
        "shap": 0.0
      }
    ],
    "hourly_risk": [
      {
        "time": "2026-05-29T00:00",
        "risk": 0.0
      },
      {
        "time": "2026-05-29T01:00",
        "risk": 0.0
      },
      {
        "time": "2026-05-29T02:00",
        "risk": 0.0
      },
      {
        "time": "2026-05-29T03:00",
        "risk": 0.0
      },
      {
        "time": "2026-05-29T04:00",
        "risk": 0.0
      },
      {
        "time": "2026-05-29T05:00",
        "risk": 0.0
      },
      {
        "time": "2026-05-29T06:00",
        "risk": 0.0
      },
      {
        "time": "2026-05-29T07:00",
        "risk": 0.0
      },
      {
        "time": "2026-05-29T08:00",
        "risk": 0.0
      },
      {
        "time": "2026-05-29T09:00",
        "risk": 0.0
      },
      {
        "time": "2026-05-29T10:00",
        "risk": 0.0
      },
      {
        "time": "2026-05-29T11:00",
        "risk": 0.0
      },
      {
        "time": "2026-05-29T12:00",
        "risk": 0.0
      },
      {
        "time": "2026-05-29T13:00",
        "risk": 0.0
      },
      {
        "time": "2026-05-29T14:00",
        "risk": 0.0
      },
      {
        "time": "2026-05-29T15:00",
        "risk": 0.0
      },
      {
        "time": "2026-05-29T16:00",
        "risk": 0.0
      },
      {
        "time": "2026-05-29T17:00",
        "risk": 0.0
      },
      {
        "time": "2026-05-29T18:00",
        "risk": 0.0
      },
      {
        "time": "2026-05-29T19:00",
        "risk": 0.0
      },
      {
        "time": "2026-05-29T20:00",
        "risk": 0.0
      },
      {
        "time": "2026-05-29T21:00",
        "risk": 0.0
      },
      {
        "time": "2026-05-29T22:00",
        "risk": 0.0
      },
      {
        "time": "2026-05-29T23:00",
        "risk": 0.0
      }
    ]
  },
  {
    "lat": 54.5,
    "lon": 20.0,
    "risk": 0.0,
    "alert": false,
    "ndvi_stress": 0.316,
    "elevation_m": 30.0,
    "slope_deg": 0.38,
    "shap_drivers": [
      {
        "feature": "wind_dryness_ratio",
        "shap": 0.0
      },
      {
        "feature": "dryness_ratio",
        "shap": 0.0
      },
      {
        "feature": "soil_x_rh",
        "shap": 0.0
      }
    ],
    "hourly_risk": [
      {
        "time": "2026-05-29T00:00",
        "risk": 0.0
      },
      {
        "time": "2026-05-29T01:00",
        "risk": 0.0
      },
      {
        "time": "2026-05-29T02:00",
        "risk": 0.0
      },
      {
        "time": "2026-05-29T03:00",
        "risk": 0.0
      },
      {
        "time": "2026-05-29T04:00",
        "risk": 0.0
      },
      {
        "time": "2026-05-29T05:00",
        "risk": 0.0
      },
      {
        "time": "2026-05-29T06:00",
        "risk": 0.0
      },
      {
        "time": "2026-05-29T07:00",
        "risk": 0.0
      },
      {
        "time": "2026-05-29T08:00",
        "risk": 0.0
      },
      {
        "time": "2026-05-29T09:00",
        "risk": 0.0
      },
      {
        "time": "2026-05-29T10:00",
        "risk": 0.0
      },
      {
        "time": "2026-05-29T11:00",
        "risk": 0.0
      },
      {
        "time": "2026-05-29T12:00",
        "risk": 0.0
      },
      {
        "time": "2026-05-29T13:00",
        "risk": 0.0
      },
      {
        "time": "2026-05-29T14:00",
        "risk": 0.0
      },
      {
        "time": "2026-05-29T15:00",
        "risk": 0.0
      },
      {
        "time": "2026-05-29T16:00",
        "risk": 0.0
      },
      {
        "time": "2026-05-29T17:00",
        "risk": 0.0
      },
      {
        "time": "2026-05-29T18:00",
        "risk": 0.0
      },
      {
        "time": "2026-05-29T19:00",
        "risk": 0.0
      },
      {
        "time": "2026-05-29T20:00",
        "risk": 0.0
      },
      {
        "time": "2026-05-29T21:00",
        "risk": 0.0
      },
      {
        "time": "2026-05-29T22:00",
        "risk": 0.0
      },
      {
        "time": "2026-05-29T23:00",
        "risk": 0.0
      }
    ]
  }
]